example.py
main.py
src/__init__.py
src/server.py
src/tools/application/__init__.py
src/tools/application/application.py
src/tools/auth/__init__.py
src/tools/auth/auth.py
src/tools/contract/__init__.py
src/tools/contract/contract.py
src/tools/workflow/__init__.py
src/tools/workflow/workflow.py
src/utils/logger/__init__.py
src/utils/logger/logger.py
tdoa_mcp_contract_filing-0.1.1.dist-info/licenses/LICENSE
tdoa_mcp_contract_filing-0.1.1.dist-info/METADATA
tdoa_mcp_contract_filing-0.1.1.dist-info/WHEEL
tdoa_mcp_contract_filing-0.1.1.dist-info/entry_points.txt
tdoa_mcp_contract_filing-0.1.1.dist-info/top_level.txt
tdoa_mcp_contract_filing-0.1.1.dist-info/RECORD
