Metadata-Version: 2.4
Name: tdoa-mcp-contract-filing
Version: 0.1.1
Summary: Tongda OA integration through the Model Context Protocol
Author-email: Liu Hao <liu.hao1443@gmail.com>
License-Expression: Apache-2.0
Project-URL: Homepage, https://github.com/LiuHao-1443/tdoa-mcp
Project-URL: Bug Tracker, https://github.com/LiuHao-1443/tdoa-mcp/issues
Requires-Python: >=3.13
License-File: LICENSE
Requires-Dist: bs4==0.0.2
Requires-Dist: fastmcp==0.4.1
Requires-Dist: loguru==0.7.3
Requires-Dist: markdown==3.7
Requires-Dist: pyyaml==6.0.2
Requires-Dist: requests==2.32.3
Dynamic: license-file
